[
  {
    "type": "Annotation",
    "body": [
      {
        "type": "TextualBody",
        "value": "Rocks",
        "purpose": "commenting"
      }
    ],
    "target": {
      "source": "https://4x4rr42s5yd4hr7mdrjqp3euqm0hnpoe.lambda-url.us-east-1.on.aws/iiif/2/1b8ccc9f6faa52ee55b2f9ea5bdb7e3e0bdfc762cd81fdb823d900878299b1f1",
      "selector": {
        "type": "FragmentSelector",
        "conformsTo": "http://www.w3.org/TR/media-frags/",
        "value": "xywh=pixel:5640.47509765625,2889.113037109375,545.1220703125,213.634521484375"
      }
    },
    "@context": "http://www.w3.org/ns/anno.jsonld",
    "id": "#78507d61-24cf-4619-a239-0c6c1f108874"
  },
  {
    "type": "Annotation",
    "body": [
      {
        "type": "TextualBody",
        "value": "Anno 3",
        "purpose": "commenting"
      }
    ],
    "target": {
      "source": "https://4x4rr42s5yd4hr7mdrjqp3euqm0hnpoe.lambda-url.us-east-1.on.aws/iiif/2/1b8ccc9f6faa52ee55b2f9ea5bdb7e3e0bdfc762cd81fdb823d900878299b1f1",
      "selector": {
        "type": "FragmentSelector",
        "conformsTo": "http://www.w3.org/TR/media-frags/",
        "value": "xywh=pixel:4305.18798828125,1829.668701171875,285.6962890625,323.422607421875"
      }
    },
    "@context": "http://www.w3.org/ns/anno.jsonld",
    "id": "#749a5ea8-133c-453d-9372-17173154f01d"
  },
  {
    "type": "Annotation",
    "body": [
      {
        "type": "TextualBody",
        "value": "test",
        "purpose": "commenting"
      }
    ],
    "target": {
      "source": "https://4x4rr42s5yd4hr7mdrjqp3euqm0hnpoe.lambda-url.us-east-1.on.aws/iiif/2/1b8ccc9f6faa52ee55b2f9ea5bdb7e3e0bdfc762cd81fdb823d900878299b1f1",
      "selector": {
        "type": "FragmentSelector",
        "conformsTo": "http://www.w3.org/TR/media-frags/",
        "value": "xywh=pixel:5158.720703125,672.1393432617188,193.70166015625,213.5245361328125"
      }
    },
    "@context": "http://www.w3.org/ns/anno.jsonld",
    "id": "#22d7264a-8565-4f2e-950b-4ad773f6c985"
  }
]